[
    {
        "_id": 1,
        "name": "Programação Funcional",
        "enq": "1º ano 1º semestre",
        "duration": "1 semester",
        "desc": "Programming with the Haskell language",
        "news": [
            {
                "title": "First news ever!",
                "description": "Primeira ficha disponível!"
            }
        ]
    },
    {
        "_id": 2,
        "name": "Programação Imperativa",
        "enq": "1º ano 2º semestre",
        "duration": "1 semester",
        "desc": "Programming with the C language"
    },
    {
        "_id": 3,
        "name": "Programação Orientada a Objetos",
        "enq": "2º ano 2º semestre",
        "duration": "1 semester",
        "desc": "Programming with the Java language"
    },
    {
        "_id": 4,
        "name": "Sistemas Operativos",
        "enq": "2º ano 2º semestre",
        "duration": "1 semester",
        "desc": "Low level programming with the C language using system calls"
    },
    {
        "_id": 5,
        "name": "Engenharia Web",
        "enq": "3º ano 2º semestre",
        "duration": "1 semester",
        "desc": "Web programming with multiple languages "
    }
]